prsmsp/__init__.py
prsmsp/panel.py
prsmsp/abstracts/__init__.py
prsmsp/abstracts/abcpanel.py
prsmsp/exceptions/__init__.py
prsmsp/exceptions/abstracts.py
prsmsp/exceptions/models.py
prsmsp/exceptions/panels.py
prsmsp/factories/__init__.py
prsmsp/factories/auth_factory.py
prsmsp/models/__init__.py
prsmsp/models/auth.py
prsmsp/models/response.py
prsmsp/panels/__init__.py
prsmsp/panels/farazsms.py
prsmsp/panels/ghasedaksms.py
prsmsp/panels/kavenegar.py
prsmsp/panels/mediana.py
prsmsp/panels/melipayamak.py
prsmsp/panels/niksms.py
prsmsp/panels/sapak.py
prsmsp/panels/smsdotir.py
prsmsp/panels/smsone.py
prsmsp/panels/webonesms.py
prsmsp-1.7.2.dist-info/METADATA
prsmsp-1.7.2.dist-info/WHEEL
prsmsp-1.7.2.dist-info/top_level.txt
prsmsp-1.7.2.dist-info/RECORD
