Metadata-Version: 2.1
Name: prsmsp
Version: 1.7.2
Summary: Package to work with sms panels
Home-page: https://github.com/parsariyahi/prsmsp
Author: Parsa Riyahi
Author-email: pany.parsariyahi@gmail.com
License: MIT License
Project-URL: Homepage, https://github.com/parsariyahi/prsmsp
Project-URL: Documentation, https://prsmsp.readthedocs.io/en/latest/
Project-URL: Source, https://github.com/parsariyahi/prsmsp
Project-URL: Tracker, https://github.com/parsariyahi/prsmsp/issues
Classifier: License :: OSI Approved :: MIT License
Classifier: Programming Language :: Python
Classifier: Programming Language :: Python :: 3
Classifier: Topic :: Software Development
Classifier: Topic :: Utilities
Classifier: Topic :: Software Development :: Libraries :: Python Modules
Requires-Python: >=3.6
Requires-Dist: requests >=2.20
